pyalbert/__init__.py
pyalbert/__main__.py
pyalbert/_logging.py
pyalbert/_version.py
pyalbert/albert.py
pyalbert/config.py
pyalbert/utils.py
pyalbert/clients/__init__.py
pyalbert/clients/albert.py
pyalbert/clients/llm_v1.py
pyalbert/clients/openai.py
pyalbert/config/rag_sources.json
pyalbert/config/whitelist_config.json
pyalbert/corpus/__init__.py
pyalbert/corpus/_download_rag_sources.py
pyalbert/corpus/loader.py
pyalbert/corpus/parser.py
pyalbert/index/__init__.py
pyalbert/index/_create_index.py
pyalbert/index/commons.py
pyalbert/index/elasticsearch.py
pyalbert/index/qdrant.py
pyalbert/lexicon/__init__.py
pyalbert/lexicon/acronyms.py
pyalbert/lexicon/institutions.py
pyalbert/lexicon/mfs_organizations.py
pyalbert/lexicon/operators_fs.py
pyalbert/prompt/__init__.py
pyalbert/prompt/postprocessing.py
pyalbert/prompt/prompt.py
pyalbert/prompt/prompt_operators.py
pyalbert/prompt/templates/analysis_prompt_template.jinja
pyalbert/prompt/templates/prompt_config.yml
pyalbert/prompt/templates/rag_gt_prompt_operators_llama_template.jinja
pyalbert/prompt/templates/rag_gt_prompt_operators_template.jinja
pyalbert/prompt/templates/rag_gt_prompt_template.jinja
pyalbert/prompt/templates/rag_prompt_template.jinja
pyalbert/schemas/__init__.py
pyalbert/schemas/llm.py
pyalbert/schemas/openai/__init__.py
pyalbert/schemas/openai/api_rag.py
pyalbert/schemas/openai/api_v1.py
pyalbert/schemas/openai/sampling_params.py
pyalbert/whitelist/__init__.py
pyalbert/whitelist/_create_whitelist.py
pyalbert/whitelist/_download_directory.py
pyalbert-0.8.0.dist-info/LICENCE
pyalbert-0.8.0.dist-info/METADATA
pyalbert-0.8.0.dist-info/WHEEL
pyalbert-0.8.0.dist-info/entry_points.txt
pyalbert-0.8.0.dist-info/top_level.txt
pyalbert-0.8.0.dist-info/RECORD
