Metadata-Version: 2.2
Name: pyalbert
Version: 0.8.0
Summary: The Albert toolkit -- CLI, libraries and lexicons
Author-email: Etalab <etalab@modernisation.gouv.fr>
License: MIT
Project-URL: Homepage, https://github.com/etalab-ia/albert
Project-URL: Source, https://github.com/etalab-ia/albert
Project-URL: Tracker, https://github.com/etalab-ia/albert/issues
Project-URL: Documentation, https://github.com/etalab-ia/albert/tree/main/docs
Keywords: IA,LLM
Requires-Python: >=3.10
License-File: LICENCE
Requires-Dist: pydantic==2.8.2
Requires-Dist: docopt-ng==0.9.0
Requires-Dist: wget==3.2
Requires-Dist: elasticsearch==8.14.0
Requires-Dist: qdrant-client==1.10.1
Requires-Dist: requests==2.32.3
Requires-Dist: beautifulsoup4==4.12.3
Requires-Dist: lxml==5.2.2
Requires-Dist: numpy==1.26.4
Requires-Dist: pandas==2.2.1
Requires-Dist: langchain-text-splitters==0.0.1
Requires-Dist: python-dotenv==1.0.1
Requires-Dist: jinja2==3.1.4
Requires-Dist: lz4==4.3.3
Requires-Dist: huggingface-hub==0.23.4
Requires-Dist: tqdm==4.66.5
Provides-Extra: test
Requires-Dist: pytest==8.2.2; extra == "test"
Provides-Extra: devops
Requires-Dist: prompt_toolkit==3.0.39; extra == "devops"
